apideck_accounting_unify/__init__.py
apideck_accounting_unify/_hooks/__init__.py
apideck_accounting_unify/_hooks/registration.py
apideck_accounting_unify/_hooks/sdkhooks.py
apideck_accounting_unify/_hooks/types.py
apideck_accounting_unify/_version.py
apideck_accounting_unify/accounting.py
apideck_accounting_unify/agedcreditors_sdk.py
apideck_accounting_unify/ageddebtors_sdk.py
apideck_accounting_unify/attachments.py
apideck_accounting_unify/balancesheet_sdk.py
apideck_accounting_unify/bankfeedaccounts.py
apideck_accounting_unify/bankfeedstatements.py
apideck_accounting_unify/basesdk.py
apideck_accounting_unify/billpayments.py
apideck_accounting_unify/bills.py
apideck_accounting_unify/companyinfo_sdk.py
apideck_accounting_unify/connectioncustommappings.py
apideck_accounting_unify/connections.py
apideck_accounting_unify/connectionsettings.py
apideck_accounting_unify/consumerrequestcounts.py
apideck_accounting_unify/consumers.py
apideck_accounting_unify/createcallback.py
apideck_accounting_unify/creditnotes.py
apideck_accounting_unify/customers.py
apideck_accounting_unify/customfields.py
apideck_accounting_unify/custommappings.py
apideck_accounting_unify/departments.py
apideck_accounting_unify/expenses.py
apideck_accounting_unify/httpclient.py
apideck_accounting_unify/invoiceitems.py
apideck_accounting_unify/invoices.py
apideck_accounting_unify/journalentries.py
apideck_accounting_unify/ledgeraccounts.py
apideck_accounting_unify/locations.py
apideck_accounting_unify/logs.py
apideck_accounting_unify/models/__init__.py
apideck_accounting_unify/models/accounting_agedcreditorsoneop.py
apideck_accounting_unify/models/accounting_ageddebtorsoneop.py
apideck_accounting_unify/models/accounting_attachmentsallop.py
apideck_accounting_unify/models/accounting_attachmentsdeleteop.py
apideck_accounting_unify/models/accounting_attachmentsdownloadop.py
apideck_accounting_unify/models/accounting_attachmentsoneop.py
apideck_accounting_unify/models/accounting_attachmentsuploadop.py
apideck_accounting_unify-0.16.2.dist-info/METADATA
apideck_accounting_unify-0.16.2.dist-info/WHEEL
apideck_accounting_unify-0.16.2.dist-info/RECORD
